Metadata-Version: 2.1
Name: tango-metrics
Version: 0.0
Summary: The first version of the own module
Home-page: UNKNOWN
Author-email: igorbenko@tango.me
License: UNKNOWN
Platform: UNKNOWN
